{
  "word": "上下",
  "pages": [
    {
      "title": "複複線",
      "surrounding": "線路(선로)끼리 묶은 것(上上下下(상상하하))이고 線路別(선로별)은 ... 方向(방향)끼리 묶은 것(上下上下(상하상하))을 意味(의미)한다",
      "count": 2
    },
    {
      "title": "𱁬",
      "surrounding": "䨺(퇴)[1]와 龘(답)[2]이 上下(상하)로 結合(결합)된 ... 字形(자형)과 單純(단순)히 上下(상하)로 結合(결합)된",
      "count": 2
    },
    {
      "title": "2020年 美合衆國 大統領選擧",
      "surrounding": "候補(후보)에게 勝利(승리)하였다 上下院(상하원) 議員(의원)",
      "count": 1
    },
    {
      "title": "中文打字機",
      "surrounding": "構成要素(구성요소)가 配列(배열)되었으며 ‘上下形檢字法(상하형검자법)’이라는 方式(방식)으로",
      "count": 1
    },
    {
      "title": "假名入力",
      "surrounding": "選擇(선택)하는 代身(대신)에 터치+上下左右(상하좌우) 각",
      "count": 1
    },
    {
      "title": "形聲文字",
      "surrounding": "會意文字(회의문자)와 마찬가지로 上下左右(상하좌우)나 안과",
      "count": 1
    },
    {
      "title": "釜山都市鐵道",
      "surrounding": "路線(노선)[편집] 釜山都市鐵道(부산도시철도) 沙上下端線(사상하단선) 特徵(특징)[편집]",
      "count": 1
    },
    {
      "title": "韓國의 漢字 問題",
      "surrounding": "된 類合(유합)과 上下(상하) 2권으로",
      "count": 1
    },
    {
      "title": "올림푸스 펜F",
      "surrounding": "像(상)을 뒤집는다 上下(상하) 或(혹)은",
      "count": 1
    },
    {
      "title": "올핌푸스 펜F",
      "surrounding": "像(상)을 뒤집는다 上下(상하) 或(혹)은",
      "count": 1
    }
  ]
}