{
  "word": "假借",
  "pages": [
    {
      "title": "韓國의 漢字 問題",
      "surrounding": "그리고 轉注字(전주자)와 假借字(가차자)가 있으나 ... 轉注(전주) 51자 假借(가차) 85자가",
      "count": 3
    },
    {
      "title": "六書",
      "surrounding": "形聲(형성) 轉注(전주) 假借(가차) ",
      "count": 1
    },
    {
      "title": "國",
      "surrounding": "걱정된다는 意味(의미)로 假借(가차)되어 ‘或是(혹시)’",
      "count": 1
    },
    {
      "title": "國漢大百科:文書作成要請",
      "surrounding": "- 轉注(전주)文字(문자) 假借(가차)文字(문자) --李！(이！)",
      "count": 1
    },
    {
      "title": "電",
      "surrounding": "쓰는 意味(의미)로 假借(가차)되면서 申(신)에",
      "count": 1
    },
    {
      "title": "𡨸喃",
      "surrounding": "그대로 쓰는 假借(가차)文字(문자)와 六書(육서)의",
      "count": 1
    }
  ]
}