{
  "word": "半數",
  "pages": [
    {
      "title": "土耳其",
      "surrounding": "어떤 政黨(정당)도 過半數(과반수)를 차지하지 ... 僅少(근소)한 差異(차이)로 過半數(과반수) 得票(득표)를",
      "count": 6
    },
    {
      "title": "韓國停戰協定",
      "surrounding": "그 中(중)의 半數(반수)는 國際聯合軍(국제연합군)(국제련합군) ... 언제나 그 半數(반수)를 超過(초과)할수없다",
      "count": 6
    },
    {
      "title": "南極條約",
      "surrounding": "가지는 締約當事國의 過半數를 包含하여 ... 參加한 締約當事國의 過半數에 依하여",
      "count": 2
    },
    {
      "title": "塞舌爾共和國",
      "surrounding": "改名(개명))李(리) 議會(의회) 過半數(과반수) 議席(의석)을 ... 다시 議會(의회) 過半數(과반수) 議席(의석)을",
      "count": 2
    },
    {
      "title": "國際聯合信託統治理事會",
      "surrounding": "安保(안보)理(리)議長(의장) 또는 安保(안보)理會(이회)員(원)國(국)過半數(과반수) 또는",
      "count": 1
    },
    {
      "title": "圭亞那",
      "surrounding": "單一(단일) 投票(투표) 過半數(과반수)는 PPP의",
      "count": 1
    },
    {
      "title": "捷克共和國",
      "surrounding": "聯邦(연방) 議會(의회)의 過半數(과반수) 議席(의석)을",
      "count": 1
    },
    {
      "title": "暮國",
      "surrounding": "上院(상원)과 下院(하원)의 過半數(과반수) 議席(의석)을",
      "count": 1
    },
    {
      "title": "歐羅巴聯合執行委員會",
      "surrounding": "383票(표)를 얻어 過半數(과반수) 差異(차이)로",
      "count": 1
    },
    {
      "title": "波蘭",
      "surrounding": "5分(분)의 3의 過半數(과반수)로 大統領(대통령)의",
      "count": 1
    },
    {
      "title": "馬來西亞",
      "surrounding": "國會(국회) 下院(하원)의 過半數(과반수) 以上(이상)의",
      "count": 1
    },
    {
      "title": "레제프 타이이프 에르도안",
      "surrounding": "第(제)1回(회) 投票(투표)로 過半數(과반수)의 票(표)를",
      "count": 1
    }
  ]
}