{
  "word": "商",
  "pages": [
    {
      "title": "西面 (釜山)",
      "surrounding": "位置(위치) 2 商業地域(상업지역) 2 ... 169-1 롯데호텔百貨店(백화점)(西面(서면)驛(역)) (西面(서면)地下商街(지하상가)方向(방향)) 17",
      "count": 9
    },
    {
      "title": "世界4大文明",
      "surrounding": "나뉘었다 經濟的(경제적)으로는 商業(상업)과 手工業者(수공업자)가 ... 하는데 이는 商(상)나라의 首都(수도)인",
      "count": 5
    },
    {
      "title": "土耳其",
      "surrounding": "代身(대신)했습니다 케말主義者(주의자)들과의 協商(협상)은 1920年(년) ... 主要(주요) 輸出(수출) 商品(상품)은 農産物(농산물)",
      "count": 5
    },
    {
      "title": "韓日基本條約",
      "surrounding": "條約(조약)은 15年間(연간)의 協商(협상) 끝에 ... 以後(이후)에 있어서의 通商(통상)의 接觸(접촉)의",
      "count": 5
    },
    {
      "title": "三星그룹",
      "surrounding": "中區(중구) 인교洞(동))에 '三(삼)星(성)商會(상회)'를 開業(개업)한 ... 생기던 때에 三(삼)星(성)商會(상회)는 地方(지방)에서",
      "count": 4
    },
    {
      "title": "密克羅尼西亞聯邦",
      "surrounding": "對(대)해 美國(미국)과 協商(협상)을 始作(시작)했다 ... 祕(비)密(밀)에 輸出(수출)하는 商品(상품)이 祕(비)密(밀)",
      "count": 4
    },
    {
      "title": "澁澤榮一",
      "surrounding": "第一國立銀行(제일국립은행)(現(현) 미즈호銀行(은행))의頭取(두취) 東京商法會議所(동경상법회의소)(現(현) 東京商工會議所(동경상공회의소))의會頭等(회두등)을歷任(역임) ... 商法講習所(상법강습소)(現(현) 一橋大學(일교대학)) 大倉商業學校(대창상업학교)(現(현) 東京經濟大學(동경경제대학))",
      "count": 4
    },
    {
      "title": "神武景氣",
      "surrounding": "勃發(발발)하여 國際(국제) 商品(상품) 時勢(시세)와 ... 商品(상품) 時勢(시세)와 海商(해상) 運賃(운임)의",
      "count": 4
    },
    {
      "title": "레제프 타이이프 에르도안",
      "surrounding": "卒業(졸업) 後(후) 이스탄불經濟商業學院(경제상업학원)(現(현) 마르마라大學校(대학교) ... İlimler Akademisi)의 商學部(상학부)(Ticarî Bilimler",
      "count": 4
    },
    {
      "title": "SC第一銀行",
      "surrounding": "1994年(년) 7月(월) 韓國商業銀行(한국상업은행)으로부터 商業證券(상업증권)을 ... 1994年(년) 9月(월)에 商業(상업)相互信用金庫(상호신용금고)(株(주))를 引受(인수)하였다",
      "count": 3
    },
    {
      "title": "和蘭",
      "surrounding": "訴訟(소송)을 心理(심리)) 通商(통상) 및 ... 합니다 2022年(년) 商品(상품) 交易(교역)",
      "count": 3
    },
    {
      "title": "商나라",
      "surrounding": "補充(보충)해 주세요 商 商(상)나라는 ... 最古(최고)의 文明(문명)이다 商(상)나라의 遺蹟(유적)이",
      "count": 3
    },
    {
      "title": "圭亞那",
      "surrounding": "需要(수요)와 深刻(심각)한 商品(상품) 不足(부족)과 ... Guyana 조지타운 商工會議所(상공회의소): 1889年(년)",
      "count": 3
    },
    {
      "title": "潛水艦",
      "surrounding": "第二次世界大戰(제이차세계대전) 모두 商業(상업) 破壞(파괴)에 ... 輸送船(수송선)에 對(대)한 商業(상업)破壞(파괴) 戰略核武器(전략핵무기)의",
      "count": 3
    },
    {
      "title": "獨-伊-日 三國同盟 條約",
      "surrounding": "위해 東京(동경)에서 協商(협상)을 벌였고 ... 協定(협정)의 延長(연장)을 協商(협상)한다 아래",
      "count": 3
    },
    {
      "title": "甲骨文字",
      "surrounding": "《古董錄(고동록)》(1933)에서 先親(선친)이 骨董商(골동상)에게서 甲骨文(갑골문)을 ... 王懿榮(왕의영)에 依(의)해 商(상)나라의 記錄(기록)임이",
      "count": 3
    },
    {
      "title": "오픈TTD",
      "surrounding": "活用(활용)하여 元來(원래) 商用(상용)소프트웨어였던 TTD를 ... 都市(도시)家口(가구)에서 받는 種類(종류)(商品(상품) 等(등))의",
      "count": 3
    },
    {
      "title": "中文打字機",
      "surrounding": "프로토타입만 만들어지고 商用化(상용화)에는 失敗(실패)한 ... 엮여 前述(전술)하였듯이 商用化(상용화)에는 失敗(실패)했고",
      "count": 2
    },
    {
      "title": "尹潽善",
      "surrounding": "結婚(결혼)) 子女(자녀) 尹琓求(윤완구)(長女(장녀))尹完姬(윤완희)(次女(차녀))尹商求(윤상구)(長男(장남))尹同求(윤동구)(次男(차남)) 宗敎(종교) ... (第(제)2代(대))(1948年(년)12月(월)15日(일)-1949年(년)6月(월)5日(일)) 大韓民國(대한민국) 商工部長官(상공부장관) (第(제)2代(대))(1949年(년)6月(월)6日(일)-1950年(년)5月(월)9日(일))",
      "count": 2
    },
    {
      "title": "日章旗",
      "surrounding": "于先(우선) 및 商船(상선)規則(규칙)(太(태)政官(정관)布告(포고) 57號(호))에서 ... 商船(상선)規則(규칙)(太(태)政官(정관)布告(포고) 57號(호))에서 商船(상선)이 내걸어야",
      "count": 2
    },
    {
      "title": "森喜朗",
      "surrounding": "第(제)85・86代(대)內閣總理大臣(내각총리대신) 第(제)62代(대)建設(건설)大臣(대신) 第(제)56代通(대통)商(상)産業(산업)大臣(대신) 第(제)105代(대)文部(문부)大臣(대신) ... 自由民主黨(자유민주당)總務(총무)會長(회장)等(등)을歷任(역임)하였다 出身地(출신지)는石(석)川(천)縣(현)이며 出身校(출신교)는早稻(조도)田(전)大學(대학)第二(제이)商學(상학)部(부) 本來(본래)",
      "count": 2
    },
    {
      "title": "機雷",
      "surrounding": "攻勢(공세)에서는 主(주)로 通商(통상)破壞(파괴)展(전)에 活用(활용)되어 ... 活用(활용)되어 敵國(적국)의 商船(상선)이나 輸送船(수송선)의",
      "count": 2
    },
    {
      "title": "殷",
      "surrounding": "殷(은)、또는商(상)은、存在(존재)가明確(명확)한 中國(중국)最古(최고)의王朝(왕조)이다。傳說上(전설상)의夏(하)王朝(왕조)의 ... 桀王(걸왕)의暴政(폭정)을滅(멸)하고、湯王(탕왕)에依(의)해 肇國(조국)되었다고傳(전)해진다。首都(수도)는當初(당초) 亳商城(박상성)에、以後亡國(이후망국)까지 殷墟(은허)에定着(정착)되었다。殷(은)은",
      "count": 2
    },
    {
      "title": "漢字直接入力",
      "surrounding": "企業(기업)에依(의)해 開發(개발)되어 商用(상용)소프트웨어로서 販賣(판매)되는 ... 먼저 聯想式(연상식) 商用(상용)소프트웨어라 進入障壁(진입장벽)부터가",
      "count": 2
    },
    {
      "title": "澳門",
      "surrounding": "中期(중기)부터 澳(오)門(문)은 商業的(상업적) 目的(목적)으로 ... 地位(지위)에 對(대)해 協商(협상)했다 그",
      "count": 2
    },
    {
      "title": "琵琶行",
      "surrounding": "今年(금년)歡笑(환소)復(복)明年(명년)，秋月(추월)春風(춘풍)等閒(등한)度(도)。 弟(제)走(주)從軍(종군)阿(아)姨(이)死(사)，暮(모)去(거)朝來(조래)顔色(안색)故(고)。 門前(문전)冷落(랭락)車馬(차마)稀(희)，老(로)大(대)嫁(가)作(작)商人(상인)婦(부)。 商人(상인)重利(중리)輕(경)別離(별리)，前月(전월)浮(부)梁(량)買(매)茶(다)去(거)。 ... 弟(제)走(주)從軍(종군)阿(아)姨(이)死(사)，暮(모)去(거)朝來(조래)顔色(안색)故(고)。 門前(문전)冷落(랭락)車馬(차마)稀(희)，老(로)大(대)嫁(가)作(작)商人(상인)婦(부)。 商人(상인)重利(중리)輕(경)別離(별리)，前月(전월)浮(부)梁(량)買(매)茶(다)去(거)。 去來(거래)江口(강구)守(수)空船(공선)，繞(요)船(선)月明(월명)江水(강수)寒(한)。",
      "count": 2
    },
    {
      "title": "秋葉原驛",
      "surrounding": "東京都區內(동경도구내)및東京山手線內(동경산수선내)에屬(속)한다。驛周邊(역주변)에는 周知(주지)된바와같이 서브컬쳐關聯商鋪(관련상포)들이櫛比(즐비)하나、驛(역)의利用者(이용자)에關(관)해서는 換乘驛(환승역)인點(점)도있어 ... 首都圈新都市鐵道(수도권신도시철도)[편집] 섬式(식)1面(면)2線(선)의地下驛(지하역)이다。[4]驛(역)빌딩으로 阪急阪神(판급판신)과共同設立(공동설립)한TX秋葉原阪急(추엽원판급)빌딩이있으며、이中商業施設(중상업시설)인 AKIBA",
      "count": 2
    },
    {
      "title": "秦나라",
      "surrounding": "秦(진) 孝(효)公(공)은 商(상)鞅(앙)을 任用(임용)하고 ... 商(상)鞅(앙)을 任用(임용)하고 商(상)鞅(앙)變法(변법)을 實施(실시)하여",
      "count": 2
    },
    {
      "title": "統一列車 달린다",
      "surrounding": "著者(저자)에게 있다 商業的(상업적)轉載(전재)는 著者(저자)에게 ... 許可(허가)를 받고 非商業的(비상업적)轉載(전재)는 出處(출처)를",
      "count": 2
    },
    {
      "title": "船橋市",
      "surrounding": "利用客(이용객)이많은것이며、市內(시내)의中心驛(중심역)은 船橋驛(선교역)이다[1]。 商業(상업)[편집] 船橋(선교)는傳統的(전통적)으로 ... 商業(상업)[편집] 船橋(선교)는傳統的(전통적)으로 商業都市(상업도시)였으며、三次産業(삼차산업)이發達(발달)되어있다。代表的(대표적)인大型商業施設(대형상업시설)로써는 東武百貨店(동무백화점)船橋店(선교점)과",
      "count": 2
    },
    {
      "title": "西西里 上陸",
      "surrounding": "補給網(보급망)은 짧았고 協商(협상)이 쉬웠다 ... 聯合國(연합국)과 祕(비)密(밀) 協商(협상)을 始作(시작)했다",
      "count": 2
    },
    {
      "title": "西面驛",
      "surrounding": "나가면 釜山(부산)最大(최대)의 商圈(상권)이자 繁華街(번화가)인 ... 釜田(부전)몰과 西面(서면)몰 地下商街(지하상가)로 이어지며",
      "count": 2
    },
    {
      "title": "金庸",
      "surrounding": "碧血劍(벽혈검) 1956年(년)1月(월)1日(일)–1956年(년)12月(월)31日(일) 香港商報(향항상보) 48 ... 射鵰英雄傳(사조영웅전) 1957年(년)1月(월)1日(일)–1959年(년)5月(월)19日(일) 香港商報(향항상보) 91",
      "count": 2
    },
    {
      "title": "鐵道唱歌 (北陸篇)",
      "surrounding": "四六 汽船の煙海をそめ 商家の軒は日をおほふ げにも五港の一つとて ... 直立九千九百尺 五二 商業繁華の高岡を すぎて福岡石動の",
      "count": 2
    },
    {
      "title": "파일:Apple-WWDC23-M2-Ultra-chip-230605 big.jpg.large.jpg",
      "surrounding": "있으며 特定(특정) 商業的(상업적) 用途(용도)로 ... 利用(이용)할 境遇(경우) 商標權(상표권) 侵害(침해)",
      "count": 2
    },
    {
      "title": "파일:Discord logo.svg",
      "surrounding": "있으며 特定(특정) 商業的(상업적) 用途(용도)로 ... 利用(이용)할 境遇(경우) 商標權(상표권) 侵害(침해)",
      "count": 2
    },
    {
      "title": "파일:Gwangju symbol.png",
      "surrounding": "있으며 特定(특정) 商業的(상업적) 用度(용도)로 ... 利用(이용)할 境遇(경우) 商標權(상표권) 侵害(침해)",
      "count": 2
    },
    {
      "title": "파일:Hn-logo.png",
      "surrounding": "있으며 特定(특정) 商業的(상업적) 用度(용도)로 ... 利用(이용)할 境遇(경우) 商標權(상표권) 侵害(침해)",
      "count": 2
    },
    {
      "title": "파일:Hq720.jpg",
      "surrounding": "있으며 特定(특정) 商業的(상업적) 用途(용도)로 ... 利用(이용)할 境遇(경우) 商標權(상표권) 侵害(침해)",
      "count": 2
    },
    {
      "title": "파일:Img 12th 05-2.gif",
      "surrounding": "있으며 特定(특정) 商業的(상업적) 用途(용도)로 ... 利用(이용)할 境遇(경우) 商標權(상표권) 侵害(침해)",
      "count": 2
    },
    {
      "title": "파일:Logo kancolle.png",
      "surrounding": "있으며 特定(특정) 商業的(상업적) 用度(용도)로 ... 利用(이용)할 境遇(경우) 商標權(상표권) 侵害(침해)",
      "count": 2
    },
    {
      "title": "파일:PrincessConnectLogo.png",
      "surrounding": "있으며 特定(특정) 商業的(상업적) 用度(용도)로 ... 利用(이용)할 境遇(경우) 商標權(상표권) 侵害(침해)",
      "count": 2
    },
    {
      "title": "파일:Tsukuyomi2.jpeg",
      "surrounding": "있으며 特定(특정) 商業的(상업적) 用途(용도)로 ... 利用(이용)할 境遇(경우) 商標權(상표권) 侵害(침해)",
      "count": 2
    },
    {
      "title": "파일:Twitter bird logo 2012.svg",
      "surrounding": "있으며 特定(특정) 商業的(상업적) 用度(용도)로 ... 利用(이용)할 境遇(경우) 商標權(상표권) 侵害(침해)",
      "count": 2
    },
    {
      "title": "파일:VAIOロゴ.png",
      "surrounding": "있으며 特定(특정) 商業的(상업적) 用度(용도)로 ... 利用(이용)할 境遇(경우) 商標權(상표권) 侵害(침해)",
      "count": 2
    },
    {
      "title": "파일:ごちうさロゴ.png",
      "surrounding": "있으며 特定(특정) 商業的(상업적) 用度(용도)로 ... 利用(이용)할 境遇(경우) 商標權(상표권) 侵害(침해)",
      "count": 2
    },
    {
      "title": "파일:成均館大學校紋章.jpg",
      "surrounding": "있으며 特定(특정) 商業的(상업적) 用度(용도)로 ... 利用(이용)할 境遇(경우) 商標權(상표권) 侵害(침해)",
      "count": 2
    },
    {
      "title": "파일:碧蓝航线logo.png",
      "surrounding": "있으며 特定(특정) 商業的(상업적) 用度(용도)로 ... 利用(이용)할 境遇(경우) 商標權(상표권) 侵害(침해)",
      "count": 2
    },
    {
      "title": "파일:語文會 로고.png",
      "surrounding": "있으며 特定(특정) 商業的(상업적) 用度(용도)로 ... 利用(이용)할 境遇(경우) 商標權(상표권) 侵害(침해)",
      "count": 2
    },
    {
      "title": "파일:더 바이너리 프로필 寫眞.jpg",
      "surrounding": "있으며 特定(특정) 商業的(상업적) 用途(용도)로 ... 利用(이용)할 境遇(경우) 商標權(상표권) 侵害(침해)",
      "count": 2
    },
    {
      "title": "파일:일본어 고등학교 교과서.jpg",
      "surrounding": "있으며 特定(특정) 商業的(상업적) 用途(용도)로 ... 利用(이용)할 境遇(경우) 商標權(상표권) 侵害(침해)",
      "count": 2
    },
    {
      "title": "파일:홀로라이브.png",
      "surrounding": "있으며 特定(특정) 商業的(상업적) 用途(용도)로 ... 利用(이용)할 境遇(경우) 商標權(상표권) 侵害(침해)",
      "count": 2
    },
    {
      "title": "7月8日",
      "surrounding": "에도만에 入港(입항)하여 通商(통상)을 要求(요구)하자",
      "count": 1
    },
    {
      "title": "DailyNK",
      "surrounding": "同時(동시)에 南北對話(남북대화) 北美(북미)協商(협상)에 關(관)한",
      "count": 1
    },
    {
      "title": "事大主義",
      "surrounding": "異樣船(이양선)들이 朝鮮(조선)에 通商(통상)을 하자",
      "count": 1
    },
    {
      "title": "人間宣言",
      "surrounding": "運輸大臣 田中武雄 商工大臣 小笠原三九郎",
      "count": 1
    },
    {
      "title": "伊太利 降伏",
      "surrounding": "바돌리오는 將軍(장군)과 協商(협상)을 始作(시작)했다",
      "count": 1
    },
    {
      "title": "伯剌西爾",
      "surrounding": "유럽聯合(연합) 間(간)의 自由貿易(자유무역)協商(협상) 妥結(타결)을",
      "count": 1
    },
    {
      "title": "利物浦",
      "surrounding": "英國(영국)의 有名(유명)한 商業(상업)中心地(중심지)이자 두",
      "count": 1
    },
    {
      "title": "千葉市",
      "surrounding": "首都圈(수도권)에서는晝間人口(주간인구)가比較的(비교적)많다。中心業務地區(중심업무지구)인 千葉都心(천엽도심)과幕張新都心(막장신도심)에는 多數(다수)의企業(기업)과商業施設等(상업시설등)이있고、一方若葉區等地(일방약엽구등지)에는 農業地(농업지)가펼쳐져、落花生(낙화생)이有名(유명)하고、臨海部(임해부)에는千葉港(천엽항)을中心(중심)으로",
      "count": 1
    },
    {
      "title": "塞舌爾共和國",
      "surrounding": "綜合(종합)共(공)예학원 藝術學(예술학)院(원) 商業(상업)과 會計學(회계학)院(원)",
      "count": 1
    },
    {
      "title": "大使",
      "surrounding": "接受國(접수국) 政府(정부)와 外交(외교)協商(협상)을 遂行(수행)하고",
      "count": 1
    },
    {
      "title": "大韓民國의 人名用 漢字",
      "surrounding": "常(상) 賞(상) 商(상) 相(상)",
      "count": 1
    },
    {
      "title": "學徒歌",
      "surrounding": "義務(의무)로다 4 農商工(농상공)業(업) 旺盛(왕성)하면",
      "count": 1
    },
    {
      "title": "室町길",
      "surrounding": "吳服店(오복점)가 늘어선 都賣商(도매상) 거리가로",
      "count": 1
    },
    {
      "title": "少女前線",
      "surrounding": "Frontline’이며 日本(일본)에서는 商標權(상표권)問題(문제)로 ‘ドールズフロントライン’(Dolls",
      "count": 1
    },
    {
      "title": "平壤直轄市",
      "surrounding": "美感(미감)이 녹아들었다 商店(상점) 食堂(식당)",
      "count": 1
    },
    {
      "title": "戰爭",
      "surrounding": "11月(월) 11日(일) 協商國(협상국) VS",
      "count": 1
    },
    {
      "title": "捷克共和國",
      "surrounding": "Lipavský 産業(산업) 通商(통상) 資源(자원)部(부)",
      "count": 1
    },
    {
      "title": "携帶用컴퓨터",
      "surrounding": " 最初의 商用 製品인",
      "count": 1
    },
    {
      "title": "新加坡",
      "surrounding": "交通(교통) 通信(통신) 商業(상업) 서비스",
      "count": 1
    },
    {
      "title": "新西蘭",
      "surrounding": "000톤의 魚貝類(어패류)가 商業的(상업적)으로 漁獲(어획)",
      "count": 1
    },
    {
      "title": "日本의 人名用 漢字",
      "surrounding": "笑 唱 商 渉",
      "count": 1
    },
    {
      "title": "春帆樓碑文(淸日講和紀念碑文)",
      "surrounding": "以後(이후) 平和(평화) 協商(협상)과 條約(조약)",
      "count": 1
    },
    {
      "title": "殷나라",
      "surrounding": "넘겨줄 대상:商나라 ",
      "count": 1
    },
    {
      "title": "漢字韓國元祖說",
      "surrounding": "미쳤다 그러나 韓國外交通商部(한국외교통상부)는 漢字(한자)",
      "count": 1
    },
    {
      "title": "漢文 敎育用 基礎 漢字",
      "surrounding": "상) • 商(상) (장사",
      "count": 1
    },
    {
      "title": "獨逸民主共和國",
      "surrounding": "間(간)의 國際(국제) 協商(협상)을 통해",
      "count": 1
    },
    {
      "title": "百﻿家姓",
      "surrounding": "梁丘(양구)左丘(좌구) 東門(동문)西門(서문) 商(상)牟(모)佘(사)佴(이) 伯(백)賞(상)南宮(남궁)",
      "count": 1
    },
    {
      "title": "秋葉原",
      "surrounding": " 電氣商店街의 風景",
      "count": 1
    },
    {
      "title": "練光亭",
      "surrounding": "沈惟敬(심유경)과 日本(일본)將軍(장군)小(소)西行(서행)長(장)의 協商(협상)場所(장소)였다 이",
      "count": 1
    },
    {
      "title": "美合衆國과 日本國 間의 相互協力 및 安全保障條約",
      "surrounding": "첫 番(번)째 協商(협상)을 가졌다",
      "count": 1
    },
    {
      "title": "美國獨立宣言",
      "surrounding": "關係(관계)를 協定(협정)하고 通商(통상) 關係(관계)를",
      "count": 1
    },
    {
      "title": "臺灣民主國",
      "surrounding": "가지고 獨逸(독일) 商船(상선) 아르투어號(호)(Arthur)에",
      "count": 1
    },
    {
      "title": "語文會 級數別 配定漢字 一覽",
      "surrounding": "仕(사) 産(산) 商(상) 相(상)",
      "count": 1
    },
    {
      "title": "越南獨立宣言",
      "surrounding": "쟁기질하는 사람들과 商人(상인)들을 가난하게",
      "count": 1
    },
    {
      "title": "金正日",
      "surrounding": "朝鮮(조선)工業銀行(공업은행) 朝鮮(조선)合(합)營(영)銀行(은행) 高麗(고려)商業銀行(상업은행)等(등) 國有(국유)銀行業(은행업)務(무)는",
      "count": 1
    },
    {
      "title": "釜田驛 (都市鐵道)",
      "surrounding": "方向(방향)으로는 ‘釜田(부전)몰 西面地下道商街(서면지하도상가)’로 連結(연결)되며",
      "count": 1
    },
    {
      "title": "鐵道唱歌(山陽-九州篇)",
      "surrounding": "二五 出船入船たえまなき 商業繁華の三田尻は 山陽線路のをはりにて",
      "count": 1
    },
    {
      "title": "鐵道唱歌(東海道篇)",
      "surrounding": "梅(うめ)田(だ)は我(われ)をむかへたり 三(さん)府(ぷ)の一(いつ)に位(くらゐ)して 商(しやう)業繁華(げふはんくわ)の大阪(おほさか)市(し) 豐太閤(ほうたいかふ)のきづきたる",
      "count": 1
    },
    {
      "title": "鐵道唱歌 (東海道篇)",
      "surrounding": "梅(うめ)田(だ)は我(われ)をむかへたり 三(さん)府(ぷ)の一(いつ)に位(くらゐ)して 商(しやう)業繁華(げふはんくわ)の大阪(おほさか)市(し) 豐太閤(ほうたいかふ)のきづきたる",
      "count": 1
    },
    {
      "title": "階級調和論",
      "surrounding": "生産者(생산자) 그룹과의 協商(협상)을 통해",
      "count": 1
    },
    {
      "title": "高速鐵道",
      "surrounding": "東海道新幹線(동해도신간선)이 世界最初(세계최초)의 商業用(상업용) 高速鐵道(고속철도)로",
      "count": 1
    },
    {
      "title": "魚雷",
      "surrounding": "全般(전반)에 걸쳐 商船(상선)을 攻擊(공격)하는",
      "count": 1
    },
    {
      "title": "게임보이",
      "surrounding": "게임으로 進行(진행)된다 商標權(상표권)을 利用(이용)하여",
      "count": 1
    },
    {
      "title": "늑대 無理 戰術",
      "surrounding": "船舶(선박) 周邊(주변)의 商船(상선)과 防禦(방어)",
      "count": 1
    },
    {
      "title": "도널드 트럼프",
      "surrounding": ")은 美合衆國(미합중국)의 商人(상인)과 政治人(정치인)이다",
      "count": 1
    },
    {
      "title": "록펠러 中心",
      "surrounding": "센터는 19個(개)의 商業(상업)用(용) 建物(건물)로",
      "count": 1
    },
    {
      "title": "빅맥",
      "surrounding": "메뉴로 맥도날드의 플래그쉽商品(상품)이다 목차",
      "count": 1
    },
    {
      "title": "새마을運動",
      "surrounding": "消費(소비)의 兩面(양면)에서 商品經濟(상품경제)가 急速(급속)히",
      "count": 1
    },
    {
      "title": "스위스鐵道時計",
      "surrounding": "繼續使用(계속사용)되고있으며、2002年(년)에 스위스聯邦鐵道(연방철도)는 이時計(시계)를立體商標(입체상표)로登錄(등록)하였다。이와關聯(관련)된事件(사건)으로 iOS",
      "count": 1
    },
    {
      "title": "아프리칸스語",
      "surrounding": "交流(교류)를 重視(중시)하는 商工業(상공업) 中心(중심)이라",
      "count": 1
    },
    {
      "title": "에어팟",
      "surrounding": "好評(호평)을 받아 人氣商品(인기상품)이 되었다",
      "count": 1
    },
    {
      "title": "유닉스",
      "surrounding": "大文字(대문자) 表記(표기)로 商標化(상표화)됨)는 多重(다중)",
      "count": 1
    },
    {
      "title": "젤다의傳說",
      "surrounding": "/ 5루피 商店(상점)에서 使用(사용)하는",
      "count": 1
    },
    {
      "title": "젤다의傳說 夢幻의 모래時計",
      "surrounding": "'테리의 배' 商店(상점)도 登場(등장)한다",
      "count": 1
    },
    {
      "title": "칼 구스타프 만네르하임",
      "surrounding": "別途(별도)의 平和(평화) 協商(협상)을 할",
      "count": 1
    },
    {
      "title": "프랭클린 D. 루스벨트",
      "surrounding": "一部(일부)는 美國(미국) 商業(상업)에서 重要(중요)한",
      "count": 1
    }
  ]
}