{
  "word": "畢",
  "pages": [
    {
      "title": "大韓民國의 人名用 漢字",
      "surrounding": "匹(필) 筆(필) 畢(필) 弼(필)",
      "count": 1
    },
    {
      "title": "日本의 人名用 漢字",
      "surrounding": "甫 畠 畢 疋",
      "count": 1
    },
    {
      "title": "漢文 敎育用 基礎 漢字",
      "surrounding": "(붓 필) 畢(필) (마칠",
      "count": 1
    },
    {
      "title": "無政府資本主義",
      "surrounding": "依(의)해 社會(사회)는 畢竟(필경) 安定(안정)에達(달)할것이라",
      "count": 1
    },
    {
      "title": "百﻿家姓",
      "surrounding": "費(비)廉(염)岑(잠)薛(설) 雷(뇌)賀(하)倪(예)湯(탕) 滕(등)殷(은)羅(나)畢(필) 郝(학)鄔(오)安(안)常(상)",
      "count": 1
    },
    {
      "title": "語文會 級數別 配定漢字 一覽",
      "surrounding": "皮(피) 彼(피) 畢(필) 荷(하)",
      "count": 1
    },
    {
      "title": "韓國停戰協定",
      "surrounding": "違反(위반)의 結果(결과)는 畢竟(필경) 戰爭(전쟁)을",
      "count": 1
    }
  ]
}