{
  "word": "邑",
  "pages": [
    {
      "title": "世宗特別自治市",
      "surrounding": "湖西地方(호서지방) 下位行政區域(하위행정구역) 1邑(읍) 9面(면) ... 設置(설치)되어 있다 鳥致院邑(조치원읍) 燕岐面(연기면)",
      "count": 4
    },
    {
      "title": "機張郡",
      "surrounding": "日光新都市(일광신도시) 行政區域(행정구역)[편집] 機張邑(기장읍) 長安邑(장안읍) ... 機張邑(기장읍) 長安邑(장안읍) 鼎冠邑(정관읍) 日光面(일광면)",
      "count": 3
    },
    {
      "title": "金正淑",
      "surrounding": "있는 郡(군) 金正淑邑(김정숙읍) - ... 金正淑郡(김정숙군)에 있는 邑(읍) ",
      "count": 2
    },
    {
      "title": "大韓民國의 人名用 漢字",
      "surrounding": "韾(음) 읍 邑(읍) 泣(읍)",
      "count": 1
    },
    {
      "title": "室町길",
      "surrounding": "日本(일본)의 古代(고대) 都邑(도읍)인 平安京(평안경)의",
      "count": 1
    },
    {
      "title": "忠淸南道",
      "surrounding": "行政區域(행정구역)[편집] 8市(시)7郡(군) 25邑(읍)136面(면)46同(동) 天安市(천안시)",
      "count": 1
    },
    {
      "title": "日本의 人名用 漢字",
      "surrounding": "遁 遼 邑 祁",
      "count": 1
    },
    {
      "title": "東京都",
      "surrounding": "“東京(동경)”은 “東(동)쪽에있는 都邑(도읍)”이라는 뜻이다",
      "count": 1
    },
    {
      "title": "東萊區",
      "surrounding": "史蹟(사적)[편집] 忠烈祠(충렬사) 東萊邑城(동래읍성) 東萊府東軒(동래부동헌)",
      "count": 1
    },
    {
      "title": "殷",
      "surrounding": "亳商城(박상성)에、以後亡國(이후망국)까지 殷墟(은허)에定着(정착)되었다。殷(은)은 邑(읍)의聯合體(연합체)인邑制國家(읍제국가)였으며、政治(정치)는占卜(점복)에依(의)해 치루어지는",
      "count": 1
    },
    {
      "title": "水營江",
      "surrounding": "釜山廣域市(부산광역시) 機張郡(기장군) 鼎冠邑(정관읍) 湧天山(용천산)",
      "count": 1
    },
    {
      "title": "沃沮",
      "surrounding": "聯盟體(연맹체)이다 君長階級(군장계급)인 邑君(읍군)과 三老(삼로)가",
      "count": 1
    },
    {
      "title": "漢文 敎育用 基礎 漢字",
      "surrounding": "음) 읍 邑(읍) (고을",
      "count": 1
    },
    {
      "title": "百濟",
      "surrounding": "河南(하남) 慰禮城(위례성)을 都邑(도읍)으로 했다",
      "count": 1
    },
    {
      "title": "神道",
      "surrounding": "無封樹(무봉수) 無立寢殿(무립침전) 造園邑(조원읍) 通神道(통신도)",
      "count": 1
    },
    {
      "title": "秦非子",
      "surrounding": "나머지 非子(비자)에게 秦邑(진읍)의 數十里(수십리)",
      "count": 1
    },
    {
      "title": "語文會 級數別 配定漢字 一覽",
      "surrounding": "有(유) 育(육) 邑(읍) 入(입)",
      "count": 1
    },
    {
      "title": "韓國語의 漢字",
      "surrounding": "ㅂ 받침은 邑(읍)이나 巴(파)로",
      "count": 1
    },
    {
      "title": "首都",
      "surrounding": "都市(도시) 類意語(유의어)로는 都邑(도읍) 서울",
      "count": 1
    },
    {
      "title": "高麗",
      "surrounding": "919年(년) 松嶽(송악)(開城(개성))으로 都邑(도읍)을 옮겼다",
      "count": 1
    },
    {
      "title": "서울市立昇華院",
      "surrounding": "옛 行政區域(행정구역)인 碧蹄邑(벽제읍)을 따서",
      "count": 1
    }
  ]
}