{
  "word": "여기에",
  "pages": [
    {
      "title": "韓國의 漢字 問題",
      "surrounding": "敎育(교육)을 廢止(폐지)함으로써 여기에서 傳統文化(전통문화)의 ... 一次的(일차적) 目的(목적)이 여기에 있다고",
      "count": 10
    },
    {
      "title": "形聲文字",
      "surrounding": "80% 以上(이상)이 여기에 屬(속)하며 ... 漢字(한자)의 大部分(대부분)이 여기에 屬(속)한다",
      "count": 2
    },
    {
      "title": "인터넷新造語",
      "surrounding": "내로남不(부) 價成比(가성비)等(등)이 여기에 屬(속)한다 ... ㅎㅇ 等(등)이 여기에 屬(속)한다",
      "count": 2
    },
    {
      "title": "CJK",
      "surrounding": "한다 背景(배경)[편집] 여기에 屬(속)하는",
      "count": 1
    },
    {
      "title": "一伊那爾栖",
      "surrounding": "'니노마에(にのまえ)'라 읽는데 여기에基因(기인)하여 말",
      "count": 1
    },
    {
      "title": "拜啓도펠겡어",
      "surrounding": "꽤나便安(편안)해서」 「이제當身(당신)의居處(거처)는 여기에없다는것 알고있잖아」",
      "count": 1
    },
    {
      "title": "拜啓도플갱어",
      "surrounding": "꽤나便安(편안)해서」 「이제當身(당신)의居處(거처)는 여기에없다는것 알고있잖아」",
      "count": 1
    },
    {
      "title": "會意文字",
      "surrounding": "休(휴) 등이 여기에 屬(속)한다",
      "count": 1
    },
    {
      "title": "歷史的假名表記法",
      "surrounding": "나타내는 假名表記法(가명표기법)에는 여기에對應(대응)되는 歷史的字音假名表記法(역사적자음가명표기법)이",
      "count": 1
    },
    {
      "title": "獨逸國",
      "surrounding": "皇帝(황제)가 되어 여기에 獨逸國(독일국)이",
      "count": 1
    },
    {
      "title": "花園明朝",
      "surrounding": "뱡)이나 𱁬(다이토)가 여기에 包含(포함)된다",
      "count": 1
    },
    {
      "title": "言語",
      "surrounding": "나비語(어) 等(등)이 여기에 屬(속)한다",
      "count": 1
    },
    {
      "title": "象形文字 (漢字)",
      "surrounding": "되는 漢字(한자)들이 여기에 該當(해당)한다",
      "count": 1
    },
    {
      "title": "韓國語 入力方式",
      "surrounding": "北韓(북한) 標準配列(표준배열)이 여기에 屬(속)한다",
      "count": 1
    },
    {
      "title": "살아갈 緣故",
      "surrounding": "내가 노래하는건 여기에 태어났기",
      "count": 1
    },
    {
      "title": "서울地下鐵 1號線",
      "surrounding": "서울交通公社(교통공사) 所屬車輛(소속차량)이 여기에 配屬(배속)된다",
      "count": 1
    }
  ]
}