{
  "word": "이르는",
  "pages": [
    {
      "title": "朝鮮民主主義人民共和國",
      "surrounding": "아니라 韓半島(한반도)를 이르는 傳統的(전통적)인 ... 民族(민족)과 文化圈(문화권)을 이르는 말로",
      "count": 2
    },
    {
      "title": "韓國停戰協定",
      "surrounding": "通(통)하는 道路(도로)에 이르는 사이에 ... 莫論(막론)하고 都市山村(도시산촌) 이르는 곳마다",
      "count": 2
    },
    {
      "title": "CJK",
      "surrounding": "日本語(일본어)를 통틀어 이르는 말로",
      "count": 1
    },
    {
      "title": "崇高한 오스만國",
      "surrounding": "우크라이나 헝가리에 이르는 廣大(광대)한",
      "count": 1
    },
    {
      "title": "市",
      "surrounding": "사고파는 市場(시장)을 이르는 漢字(한자)이다",
      "count": 1
    },
    {
      "title": "漢字韓國元祖說",
      "surrounding": "朝陽(조양)에서 襄平(양평)에 이르는 長城(장성)을",
      "count": 1
    },
    {
      "title": "純우리말",
      "surrounding": "韓國語(한국어)에서 固有語(고유어)를 이르는 말이다",
      "count": 1
    },
    {
      "title": "芳文社",
      "surrounding": "이러한歷史(역사)에相應(상응)하게 創立後(창립후) 現在(현재)에이르는 70餘年間(여년간)",
      "count": 1
    },
    {
      "title": "音盤",
      "surrounding": "物件(물건)을 통틀어 이르는 말",
      "count": 1
    },
    {
      "title": "한글",
      "surrounding": "頒布(반포)된 音素文字(음소문자)를 이르는 말이며",
      "count": 1
    }
  ]
}