{
  "word": "중앙선",
  "pages": [
    {
      "title": "中央線",
      "surrounding": "2 道路(도로)의 中央線(중앙선) 3 ... 본선(ちゅうおうほんせん) 大韓民國(대한민국) 中央線(중앙선)의 立地(입지)와",
      "count": 11
    },
    {
      "title": "韓國高速鐵道",
      "surrounding": "京江線(경강선) (萬鍾(만종)~江陵(강릉)) 中央線(중앙선) (淸凉里(청량리)-嶋潭(도담)) ... 開通(개통) 2021年(년)1月(월)5日(일) 中央線(중앙선) 系統(계통)",
      "count": 3
    },
    {
      "title": "KTX-이음",
      "surrounding": "[1] 路線(노선)[編輯] 中央線(중앙선) 江陵(강릉)線(선) ... EMU-260이 最初(최초)로公開(공개)되고 中央線(중앙선)과 京江(경강)線(선)에서",
      "count": 2
    },
    {
      "title": "2021年",
      "surrounding": "事件(사건)[編輯] 1月(월)5日(일) 中央線(중앙선)에서 KTX-이음이",
      "count": 1
    },
    {
      "title": "世宗特別自治市",
      "surrounding": "2002年(년) 民主黨(민주당) 中央選擧對策委員會(중앙선거대책위원회) 出帆式(출범식)에서",
      "count": 1
    },
    {
      "title": "首都圈電鐵",
      "surrounding": "仁川(인천)國際空港(국제공항)鐵道(철도) 首都圈(수도권)電鐵(전철) 京(경)義(의)·中央線(중앙선) 首都圈(수도권)電鐵(전철)",
      "count": 1
    },
    {
      "title": "서울地下鐵 7號線",
      "surrounding": "上(상)鳳(봉)驛(역) - 京(경)義(의)·中央線(중앙선) 京春線(경춘선)",
      "count": 1
    },
    {
      "title": "서울特別市",
      "surrounding": "京義線(경의선) 京元線(경원선) 中央線(중앙선) 首都圈(수도권)廣域(광역)鐵道(철도)",
      "count": 1
    }
  ]
}